app_store_scraper/__init__.py
app_store_scraper/__version__.py
app_store_scraper/app_store.py
app_store_scraper/base.py
app_store_scraper/podcast.py
app_store_scraper-0.3.5.dist-info/LICENCE
app_store_scraper-0.3.5.dist-info/METADATA
app_store_scraper-0.3.5.dist-info/WHEEL
app_store_scraper-0.3.5.dist-info/top_level.txt
app_store_scraper-0.3.5.dist-info/RECORD
