Metadata-Version: 2.1
Name: app-store-scraper
Version: 0.3.5
Summary: Single API ☝ App Store Review Scraper 🧹
Home-page: https://github.com/cowboy-bebug/app-store-scraper
Author: Eric Lim
License: MIT
Project-URL: Source, https://github.com/cowboy-bebug/app-store-scraper
Keywords: app store,ios,ios apps,podcasts,review,scraping,scraper
Platform: UNKNOWN
Classifier: Intended Audience :: Developers
Classifier: License :: OSI Approved :: MIT License
Classifier: Natural Language :: English
Classifier: Operating System :: OS Independent
Classifier: Programming Language :: Python :: 3
Classifier: Programming Language :: Python :: 3.6
Classifier: Programming Language :: Python :: 3.7
Classifier: Programming Language :: Python :: 3.8
Classifier: Topic :: Internet :: WWW/HTTP
Classifier: Topic :: Scientific/Engineering :: Information Analysis
Requires-Python: >=3.6
